Workbook

Sheet Cover Page
C11: DCF Model
C13: Table of Contents
C15: DCF Model
C16: 3-Statement Model

Sheet DCF Model
B1: In Millions Of $
B3: DCF Model
B5: Assumptions
B6: Tax Rate | D6: =' 3-Statement Model'!$M$14 -> 0.16806955
B7: Discount Rate | D7: 0.09
B8: Perpetural Growth Rate | D8: 0.025
B9: EV/EBITDA Mulltiple | D9: 20.0x
B10: Transaction Date | D10: 45838
B11: Fiscal Year End | D11: 45838
B12: Current Price | D12: 384.41
B13: Shares Outstanding | D13: 7465
B14: Debt | D14: =' 3-Statement Model'!H51 -> 60588
B15: Cash | D15: =' 3-Statement Model'!H43 -> 30242
B16: Capex | D16: =' 3-Statement Model'!M18 -> -40255.25
B18: Discounted Cash Flow | D18: Entry | E18: =2026 -> 2026 | F18: =E18+1 -> 2027 | G18: =F18+1 -> 2028 | H18: =G18+1 -> 2029 | I18: =H18+1 -> 2030 | J18: Exit
B19: Date | D19: 45838 | E19: =D19+365 -> 46203 | F19: =E19+365 -> 46568 | G19: =F19+366 -> 46934 | H19: =G19+365 -> 47299 | I19: =H19+365 -> 47664 | J19: =I19 -> 47664 | L19: Terminal Value
B20: EBIT | D20: - | E20: =' 3-Statement Model'!I34 -> 140028.13 | F20: =' 3-Statement Model'!J34 -> 157524.24 | G20: =' 3-Statement Model'!K34 -> 177206.45 | H20: =' 3-Statement Model'!L34 -> 199347.89 | I20: =' 3-Statement Model'!M34 -> 224255.84 | J20: - | L20: Perpetual Growth | N20: =((I25)*(1+$D$8)/($D$7-$D$8)) -> 2751771.4
B21: Less: Cash Taxes | D21: - | E21: =E20*$D$6 -> 23534.464 | F21: =F20*$D$6 -> 26475.029 | G21: =G20*$D$6 -> 29783.008 | H21: =H20*$D$6 -> 33504.31 | I21: =I20*$D$6 -> 37690.579 | J21: - | L21: Average | N21: =AVERAGE(N20,N22) -> 3995349.9
B22: Plus: D&A | D22: - | E22: =' 3-Statement Model'!I66 -> 33550.679 | F22: =' 3-Statement Model'!J66 -> 34529.589 | G22: =' 3-Statement Model'!K66 -> 35365.573 | H22: =' 3-Statement Model'!L66 -> 36079.497 | I22: =' 3-Statement Model'!M66 -> 36689.184 | J22: - | L22: EV/EBITDA | N22: =((I20+I21)*20) -> 5238928.5
B23: Less: Capex | D23: - | E23: =ABS(' 3-Statement Model'!I72) -> 40255.25 | F23: =ABS(' 3-Statement Model'!J72) -> 40255.25 | G23: =ABS(' 3-Statement Model'!K72) -> 40255.25 | H23: =ABS(' 3-Statement Model'!L72) -> 40255.25 | I23: =ABS(' 3-Statement Model'!M72) -> 40255.25 | J23: -
B24: Less: Changes in NWC | D24: - | E24: =' 3-Statement Model'!I92 -> 4647.5138 | F24: =' 3-Statement Model'!J92 -> 5968.2902 | G24: =' 3-Statement Model'!K92 -> 6714.0111 | H24: =' 3-Statement Model'!L92 -> 7552.9077 | I24: =' 3-Statement Model'!M92 -> 8496.6221 | J24: -
B25: Unlevered FCF | D25: - | E25: =((E20)-(E21)+(E22)-(E23)-(E24)) -> 105141.58 | F25: =((F20)-(F21)+(F22)-(F23)-(F24)) -> 119355.26 | G25: =((G20)-(G21)+(G22)-(G23)-(G24)) -> 135819.75 | H25: =((H20)-(H21)+(H22)-(H23)-(H24)) -> 154114.92 | I25: =((I20)-(I21)+(I22)-(I23)-(I24)) -> 174502.58 | J25: -
B26: (Entry)/Exit | D26: =-I34 -> -2899966.7 | J26: =N21 -> 3995349.9
B27: Transaction CF | D27: =D26 -> -2899966.7 | E27: =E25 -> 105141.58 | F27: =F25 -> 119355.26 | G27: =G25 -> 135819.75 | H27: =H25 -> 154114.92 | I27: =I25 -> 174502.58 | J27: =I27+J26 -> 4169852.5
B30: Intrinsic Value | G30: Market Value | L30: Rate of Return
B31: Enterprise Value | D31: =E25/(1+$D$7)^1+F25/(1+$D$7)^2+G25/(1+$D$7)^3+H25/(1+$D$7)^4+I25/(1+$D$7)^5+J26/(1+$D$7)^5 -> 3121093.8 | G31: Market Cap | I31: =D13*D12 -> 2869620.7 | L31: Target Price Upside | N31: =(N37/N35-1) -> 0.077057969
B32: Plus: Cash | D32: =+D15 -> 30242 | G32: Plus: Debt | I32: =D14 -> 60588 | L32: Internal Rate of Return (IRR) | N32: =IRR(D27:J27) -> 0.097473146
B33: Less: Debt | D33: =+D14 -> 60588 | G33: Less: Cash | I33: =+D15 -> 30242
B34: Equity Value | D34: =D31+D32-D33 -> 3090747.8 | G34: Enterprise Value | I34: =I31+I32-I33 -> 2899966.7 | L34: Market Value vs Intrinsic Value
L35: Market Value | N35: =I36 -> 384.41
B36: Equity Value/Share | D36: =D34/D13 -> 414.03185 | G36: Equity Value/Share | I36: =D12 -> 384.41 | L36: Upside | N36: =N37/N35-1 -> 0.077057969
L37: Intrinsic Value | N37: =D36 -> 414.03185

Sheet  3-Statement Model
D1: Historical Results | I1: Forecast Period
A2: In Millions of US $ | D2: 2021 | E2: =+D2+1 -> 2022 | F2: =+E2+1 -> 2023 | G2: =+F2+1 -> 2024 | H2: =+G2+1 -> 2025 | I2: =+H2+1 -> 2026 | J2: =+I2+1 -> 2027 | K2: =+J2+1 -> 2028 | L2: =+K2+1 -> 2029 | M2: =+L2+1 -> 2030
A5: Assumptions
A7: Key Assumptions
A8: Revenue Growth (% Change) | D8: - | E8: - | F8: =(F26/E26)-1 -> 0.068820296 | G8: =(G26/F26)-1 -> 0.15669962 | H8: =(H26/G26)-1 -> 0.14932156 | I8: =AVERAGE($F$8:$H$8) -> 0.12494716 | J8: =AVERAGE($F$8:$H$8) -> 0.12494716 | K8: =AVERAGE($F$8:$H$8) -> 0.12494716 | L8: =AVERAGE($F$8:$H$8) -> 0.12494716 | M8: =AVERAGE($F$8:$H$8) -> 0.12494716
A9: Cost of Goods Sold (% of Revenue) | D9: - | E9: =E27/E26 -> 0.31598326 | F9: =F27/F26 -> 0.31079914 | G9: =G27/G26 -> 0.30235556 | H9: =H27/H26 -> 0.31176258 | I9: =AVERAGE($E$9:$H$9) -> 0.31022513 | J9: =AVERAGE($E$9:$H$9) -> 0.31022513 | K9: =AVERAGE($E$9:$H$9) -> 0.31022513 | L9: =AVERAGE($E$9:$H$9) -> 0.31022513 | M9: =AVERAGE($E$9:$H$9) -> 0.31022513
A10: Salaries and Benefits (% of Revenue) | D10: - | E10: =E31/E26 -> 0.13983457 | F10: =F31/F26 -> 0.1431423 | G10: =G31/G26 -> 0.13081241 | H10: =H31/H26 -> 0.11669932 | I10: =AVERAGE($E$10:$H$10) -> 0.13262215 | J10: =AVERAGE($E$10:$H$10) -> 0.13262215 | K10: =AVERAGE($E$10:$H$10) -> 0.13262215 | L10: =AVERAGE($E$10:$H$10) -> 0.13262215 | M10: =AVERAGE($E$10:$H$10) -> 0.13262215
A11: Rent and Overhead ($000's) | D11: - | E11: 0 | F11: 0 | G11: 0 | H11: 0 | I11: =H11 -> 0 | J11: =I11 -> 0 | K11: =J11 -> 0 | L11: =K11 -> 0 | M11: =L11 -> 0
A12: Depreciation & Amortization (% of PP&E) | D12: - | E12: =E66/E46 -> 0.16517031 | F12: =F66/F46 -> 0.12602398 | G12: =G66/G46 -> 0.14420389 | H12: =H66/H46 -> 0.14862765 | I12: =AVERAGE($E$12:$H$12) -> 0.14600646 | J12: =AVERAGE($E$12:$H$12) -> 0.14600646 | K12: =AVERAGE($E$12:$H$12) -> 0.14600646 | L12: =AVERAGE($E$12:$H$12) -> 0.14600646 | M12: =AVERAGE($E$12:$H$12) -> 0.14600646
A13: Interest (% of Debt) | D13: - | E13: 0 | F13: 0 | G13: 0 | H13: 0 | I13: =H13 -> 0 | J13: =I13 -> 0 | K13: =J13 -> 0 | L13: =K13 -> 0 | M13: =L13 -> 0
A14: Tax Rate (% of Earnings Before Tax) | D14: - | E14: =E36/E34 -> 0.13165753 | F14: =F36/F34 -> 0.19147566 | G14: =G36/G34 -> 0.17957106 | H14: =H36/H34 -> 0.16957394 | I14: =AVERAGE($E$14:$H$14) -> 0.16806955 | J14: =AVERAGE($E$14:$H$14) -> 0.16806955 | K14: =AVERAGE($E$14:$H$14) -> 0.16806955 | L14: =AVERAGE($E$14:$H$14) -> 0.16806955 | M14: =AVERAGE($E$14:$H$14) -> 0.16806955
A15: Accounts Receivable (Days) | D15: - | E15: =((E44/E26)*365) -> 81.481137 | F15: =((F44/F26)*365) -> 83.859661 | G15: =((G44/G26)*365) -> 84.762934 | H15: =((H44/H26)*365) -> 90.568517 | I15: =AVERAGE($E$15:$H$15) -> 85.168062 | J15: =AVERAGE($E$15:$H$15) -> 85.168062 | K15: =AVERAGE($E$15:$H$15) -> 85.168062 | L15: =AVERAGE($E$15:$H$15) -> 85.168062 | M15: =AVERAGE($E$15:$H$15) -> 85.168062
A16: Inventory (Days) | D16: - | E16: =((E45/E27)*365) -> 21.800958 | F16: =((F45/F27)*365) -> 13.854516 | G16: =((G45/G27)*365) -> 6.1363575 | H16: =((H45/H27)*365) -> 3.8980542 | I16: =AVERAGE($E$16:$H$16) -> 11.422471 | J16: =AVERAGE($E$16:$H$16) -> 11.422471 | K16: =AVERAGE($E$16:$H$16) -> 11.422471 | L16: =AVERAGE($E$16:$H$16) -> 11.422471 | M16: =AVERAGE($E$16:$H$16) -> 11.422471
A17: Accounts Payable (Days) | D17: - | E17: =(E50/E27)*365 -> 110.69433 | F17: =(F50/F27)*365 -> 100.27899 | G17: =(G50/G27)*365 -> 108.3269 | H17: =(H50/H27)*365 -> 115.21285 | I17: =AVERAGE($E$17:$H$17) -> 108.62827 | J17: =AVERAGE($E$17:$H$17) -> 108.62827 | K17: =AVERAGE($E$17:$H$17) -> 108.62827 | L17: =AVERAGE($E$17:$H$17) -> 108.62827 | M17: =AVERAGE($E$17:$H$17) -> 108.62827
A18: Capital Expenditures ($000's) | D18: - | E18: =E71 -> -23886 | F18: =F71 -> -28107 | G18: =G71 -> -44477 | H18: =H71 -> -64551 | I18: =AVERAGE($E$18:$H$18) -> -40255.25 | J18: =AVERAGE($E$18:$H$18) -> -40255.25 | K18: =AVERAGE($E$18:$H$18) -> -40255.25 | L18: =AVERAGE($E$18:$H$18) -> -40255.25 | M18: =AVERAGE($E$18:$H$18) -> -40255.25
A19: Debt Issuance (Repayment) ($000's) | D19: - | E19: =E75 -> -9023 | F19: =F75 -> -2750 | G19: =G75 -> -4675 | H19: =H75 -> -3216 | I19: =AVERAGE($E$19:$H$19) -> -4916 | J19: =AVERAGE($E$19:$H$19) -> -4916 | K19: =AVERAGE($E$19:$H$19) -> -4916 | L19: =AVERAGE($E$19:$H$19) -> -4916 | M19: =AVERAGE($E$19:$H$19) -> -4916
A20: Equity Issued (Repaid) ($000's) | D20: - | E20: =E76 -> -30855 | F20: =F76 -> -20379 | G20: =G76 -> -15252 | H20: =H76 -> -16364 | I20: =AVERAGE($E$20:$H$20) -> -20712.5 | J20: =AVERAGE($E$20:$H$20) -> -20712.5 | K20: =AVERAGE($E$20:$H$20) -> -20712.5 | L20: =AVERAGE($E$20:$H$20) -> -20712.5 | M20: =AVERAGE($E$20:$H$20) -> -20712.5
A21: Days in Period | D21: - | E21: 365 | F21: 365 | G21: 365 | H21: 365 | I21: =AVERAGE(E21:H21) -> 365 | J21: =AVERAGE(F21:I21) -> 365 | K21: =AVERAGE(G21:J21) -> 365 | L21: =AVERAGE(H21:K21) -> 365 | M21: =AVERAGE(I21:L21) -> 365
A24: Income Statement
A26: Revenue | D26: - | E26: 198270 | F26: 211915 | G26: 245122 | H26: 281724 | I26: =((H26)*(1+I8)) -> 316924.61 | J26: =((I26)*(1+J8)) -> 356523.44 | K26: =((J26)*(1+K8)) -> 401070.04 | L26: =((K26)*(1+L8)) -> 451182.6 | M26: =((L26)*(1+M8)) -> 507556.58
A27: Cost of Goods Sold (COGS) | D27: - | E27: 62650 | F27: 65863 | G27: 74114 | H27: 87831 | I27: =((I26)*I9) -> 98317.981 | J27: =((J26)*J9) -> 110602.53 | K27: =((K26)*K9) -> 124422.01 | L27: =((L26)*L9) -> 139968.18 | M27: =((M26)*M9) -> 157456.81
A28: Gross Profit | D28: - | E28: 135620 | F28: 146052 | G28: 171008 | H28: 193893 | I28: =I26-I27 -> 218606.63 | J28: =J26-J27 -> 245920.91 | K28: =K26-K27 -> 276648.03 | L28: =L26-L27 -> 311214.42 | M28: =M26-M27 -> 350099.77
A29: Expenses | D29: -
A30: Research and Development Expenses | D30: - | E30: 24512 | F30: 27195 | G30: 29510 | H30: 32488 | I30: =((H30*(1+I8))) -> 36547.283 | J30: =((I30*(1+J8))) -> 41113.763 | K30: =((J30*(1+K8))) -> 46250.81 | L30: =((K30*(1+L8))) -> 52029.718 | M30: =((L30*(1+M8))) -> 58530.683
A31: SG&A Expenses | D31: - | E31: 27725 | F31: 30334 | G31: 32065 | H31: 32877 | I31: =((I26)*(I10)) -> 42031.224 | J31: =((J26)*(J10)) -> 47282.906 | K31: =((K26)*(K10)) -> 53190.77 | L31: =((L26)*(L10)) -> 59836.806 | M31: =((M26)*(M10)) -> 67313.245
A32: Other Operating Income or Expenses | D32: - | E32: - | F32: - | G32: - | H32: - | I32: - | J32: - | K32: - | L32: - | M32: -
A33: Total Expenses | D33: - | E33: =SUM(E30,E31,E32) -> 52237 | F33: =SUM(F30,F31,F32) -> 57529 | G33: =SUM(G30,G31,G32) -> 61575 | H33: =SUM(H30,H31,H32) -> 65365 | I33: =SUM(I30,I31,I32) -> 78578.507 | J33: =SUM(J30,J31,J32) -> 88396.668 | K33: =SUM(K30,K31,K32) -> 99441.581 | L33: =SUM(L30,L31,L32) -> 111866.52 | M33: =SUM(M30,M31,M32) -> 125843.93
A34: Earnings Before Tax | D34: - | E34: =(E28-E33) -> 83383 | F34: =(F28-F33) -> 88523 | G34: =(G28-G33) -> 109433 | H34: =(H28-H33) -> 128528 | I34: =(I28-I33) -> 140028.13 | J34: =(J28-J33) -> 157524.24 | K34: =(K28-K33) -> 177206.45 | L34: =(L28-L33) -> 199347.89 | M34: =(M28-M33) -> 224255.84
A36: Taxes | D36: - | E36: 10978 | F36: 16950 | G36: 19651 | H36: 21795 | I36: =((I34*I14)) -> 23534.464 | J36: =((J34*J14)) -> 26475.029 | K36: =((K34*K14)) -> 29783.008 | L36: =((L34*L14)) -> 33504.31 | M36: =((M34*M14)) -> 37690.579
A37: Net Earnings | D37: - | E37: =E34-E36 -> 72405 | F37: =F34-F36 -> 71573 | G37: =G34-G36 -> 89782 | H37: =H34-H36 -> 106733 | I37: =I34-I36 -> 116493.66 | J37: =J34-J36 -> 131049.21 | K37: =K34-K36 -> 147423.44 | L37: =L34-L36 -> 165843.58 | M37: =M34-M36 -> 186565.27
A40: Balance Sheet
A42: Assets
A43: Cash | D43: - | E43: 13931 | F43: 34704 | G43: 18315 | H43: 30242 | I43: =I81 -> 109755.08 | J43: =J81 -> 203481.84 | K43: =K81 -> 313673.09 | L43: =L81 -> 442159.51 | M43: =M81 -> 591033.59
A44: Accounts Receivable | D44: - | E44: 44261 | F44: 48688 | G44: 56924 | H44: 69905 | I44: =((I26/365)*I15) -> 73950.288 | J44: =((J26/365)*J15) -> 83190.167 | K44: =((K26/365)*K15) -> 93584.542 | L44: =((L26/365)*L15) -> 105277.66 | M44: =((M26/365)*M15) -> 118431.81
A45: Inventory | D45: - | E45: 3742 | F45: 2500 | G45: 1246 | H45: 938 | I45: =((I27/365)*I16) -> 3076.8064 | J45: =((J27/365)*J16) -> 3461.2446 | K45: =((K27/365)*K16) -> 3893.7173 | L45: =((L27/365)*L16) -> 4380.2262 | M45: =((M27/365)*M16) -> 4927.523
A46: Property & Equipment | D46: - | E46: 87546 | F46: 109987 | G46: 154552 | H46: 229789 | I46: =I98 -> 236493.57 | J46: =J98 -> 242219.23 | K46: =K98 -> 247108.91 | L46: =L98 -> 251284.66 | M46: =M98 -> 254850.73
A47: Total Assets | D47: - | E47: =SUM(E43,E44,E45,E46) -> 149480 | F47: =SUM(F43,F44,F45,F46) -> 195879 | G47: =SUM(G43,G44,G45,G46) -> 231037 | H47: =SUM(H43,H44,H45,H46) -> 330874 | I47: =SUM(I43:I46) -> 423275.74 | J47: =SUM(J43:J46) -> 532352.48 | K47: =SUM(K43:K46) -> 658260.26 | L47: =SUM(L43:L46) -> 803102.07 | M47: =SUM(M43:M46) -> 969243.65
A49: Liabilities
A50: Accounts Payable | D50: - | E50: 19000 | F50: 18095 | G50: 21996 | H50: 27724 | I50: =((I27/365*I17)) -> 29260.581 | J50: =((J27/365*J17)) -> 32916.607 | K50: =((K27/365*K17)) -> 37029.444 | L50: =((L27/365*L17)) -> 41656.168 | M50: =((M27/365*M17)) -> 46860.988
A51: Debt | D51: - | E51: 61270 | F51: 59965 | G51: 67127 | H51: 60588 | I51: =(H51+I19) -> 55672 | J51: =(I51+J19) -> 50756 | K51: =(J51+K19) -> 45840 | L51: =(K51+L19) -> 40924 | M51: =(L51+M19) -> 36008
A52: Total Liabilities | D52: - | E52: =SUM(E50,E51) -> 80270 | F52: =SUM(F50,F51) -> 78060 | G52: =SUM(G50,G51) -> 89123 | H52: =SUM(H50,H51) -> 88312 | I52: =SUM(I50:I51) -> 84932.581 | J52: =SUM(J50:J51) -> 83672.607 | K52: =SUM(K50:K51) -> 82869.444 | L52: =SUM(L50:L51) -> 82580.168 | M52: =SUM(M50:M51) -> 82868.988
A53: Shareholder's Equity
A54: Equity Capital | D54: - | E54: 86939 | F54: 93718 | G54: 100923 | H54: 109095 | I54: =(H54+I20) -> 88382.5 | J54: =(I54+J20) -> 67670 | K54: =(J54+K20) -> 46957.5 | L54: =(K54+L20) -> 26245 | M54: =(L54+M20) -> 5532.5
A55: Retained Earnings | D55: - | E55: 84281 | F55: 118848 | G55: 173144 | H55: 237731 | I55: =H55+I37 -> 354224.66 | J55: =I55+J37 -> 485273.88 | K55: =J55+K37 -> 632697.32 | L55: =K55+L37 -> 798540.9 | M55: =L55+M37 -> 985106.16
A56: Shareholder's Equity | D56: - | E56: =SUM(E54:E55) -> 171220 | F56: =SUM(F54:F55) -> 212566 | G56: =SUM(G54:G55) -> 274067 | H56: =SUM(H54:H55) -> 346826 | I56: =SUM(I54:I55) -> 442607.16 | J56: =SUM(J54:J55) -> 552943.88 | K56: =SUM(K54:K55) -> 679654.82 | L56: =SUM(L54:L55) -> 824785.9 | M56: =SUM(M54:M55) -> 990638.66
A57: Total Liabilities & Shareholder's Equity | D57: - | E57: =(E52+E56) -> 251490 | F57: =(F52+F56) -> 290626 | G57: =(G52+G56) -> 363190 | H57: =(H52+H56) -> 435138 | I57: =(I52+I56) -> 527539.74 | J57: =(J52+J56) -> 636616.48 | K57: =(K52+K56) -> 762524.26 | L57: =(L52+L56) -> 907366.07 | M57: =(M52+M56) -> 1073507.7
A62: Cash Flow Statement
A64: Operating Cash Flow
A65: Net Earnings | D65: - | E65: 72738 | F65: 72631 | G65: 88136 | H65: 101832 | I65: =I37 -> 116493.66 | J65: =J37 -> 131049.21 | K65: =K37 -> 147423.44 | L65: =L37 -> 165843.58 | M65: =M37 -> 186565.27
A66: Plus: Depreciation & Amortization | D66: - | E66: 14460 | F66: 13861 | G66: 22287 | H66: 34153 | I66: =I97 -> 33550.679 | J66: =J97 -> 34529.589 | K66: =K97 -> 35365.573 | L66: =L97 -> 36079.497 | M66: =M97 -> 36689.184
A67: Less: Changes in Working Capital | D67: - | E67: =446000/1000 -> 446 | F67: =-2388000/1000 -> -2388 | G67: =1824000/1000 -> 1824 | H67: -5350 | I67: =I92 -> 4647.5138 | J67: =J92 -> 5968.2902 | K67: =K92 -> 6714.0111 | L67: =L92 -> 7552.9077 | M67: =M92 -> 8496.6221
A68: Cash from Operations | D68: - | E68: =((E65+E66)-E67) -> 86752 | F68: =((F65+F66)-F67) -> 88880 | G68: =((G65+G66)-G67) -> 108599 | H68: =((H65+H66)-H67) -> 141335 | I68: =((I65+I66)-I67) -> 145396.83 | J68: =((J65+J66)-J67) -> 159610.51 | K68: =((K65+K66)-K67) -> 176075 | L68: =((L65+L66)-L67) -> 194370.17 | M68: =((M65+M66)-M67) -> 214757.83
A70: Investing Cash Flow
A71: Investments in Property & Equipment | D71: - | E71: -23886 | F71: -28107 | G71: =-44477 -> -44477 | H71: -64551 | I71: =I18 -> -40255.25 | J71: =J18 -> -40255.25 | K71: =K18 -> -40255.25 | L71: =L18 -> -40255.25 | M71: =M18 -> -40255.25
A72: Cash from Investing | D72: - | E72: =E71 -> -23886 | F72: =F71 -> -28107 | G72: =G71 -> -44477 | H72: =H71 -> -64551 | I72: =I71 -> -40255.25 | J72: =J71 -> -40255.25 | K72: =K71 -> -40255.25 | L72: =L71 -> -40255.25 | M72: =M71 -> -40255.25
A74: Financing Cash Flow
A75: Issuance (repayment) of debt | D75: - | E75: =0+-9023 -> -9023 | F75: =(0+-2750) -> -2750 | G75: =24395+(-29070) -> -4675 | H75: =(0+-3216) -> -3216 | I75: =I102 -> -4916 | J75: =J102 -> -4916 | K75: =K102 -> -4916 | L75: =L102 -> -4916 | M75: =M102 -> -4916
A76: Issuance (repayment) of equity | D76: - | E76: =1841-32696 -> -30855 | F76: =1866-22245 -> -20379 | G76: =2002-17254 -> -15252 | H76: =2056-18420 -> -16364 | I76: =I20 -> -20712.5 | J76: =J20 -> -20712.5 | K76: =K20 -> -20712.5 | L76: =L20 -> -20712.5 | M76: =M20 -> -20712.5
A77: Cash from Financing | D77: - | E77: =SUM(E75:E76) -> -39878 | F77: =SUM(F75:F76) -> -23129 | G77: =SUM(G75:G76) -> -19927 | H77: =SUM(H75:H76) -> -19580 | I77: =SUM(I75:I76) -> -25628.5 | J77: =SUM(J75:J76) -> -25628.5 | K77: =SUM(K75:K76) -> -25628.5 | L77: =SUM(L75:L76) -> -25628.5 | M77: =SUM(M75:M76) -> -25628.5
A79: Net Increase (decrease) in Cash | D79: - | E79: =E77+E72+E68 -> 22988 | F79: =F77+F72+F68 -> 37644 | G79: =G77+G72+G68 -> 44195 | H79: =H77+H72+H68 -> 57204 | I79: =I77+I72+I68 -> 79513.077 | J79: =J77+J72+J68 -> 93726.763 | K79: =K77+K72+K68 -> 110191.25 | L79: =L77+L72+L68 -> 128486.42 | M79: =M77+M72+M68 -> 148874.08
A80: Opening Cash Balance | D80: - | E80: 14224 | F80: =E81 -> 13931 | G80: =F81 -> 34704 | H80: =G81 -> 18315 | I80: =H81 -> 30242 | J80: =I81 -> 109755.08 | K80: =J81 -> 203481.84 | L80: =K81 -> 313673.09 | M80: =L81 -> 442159.51
A81: Closing Cash Balance | D81: - | E81: =E43 -> 13931 | F81: =F43 -> 34704 | G81: =G43 -> 18315 | H81: =H43 -> 30242 | I81: =SUM(I79:I80) -> 109755.08 | J81: =SUM(J79:J80) -> 203481.84 | K81: =SUM(K79:K80) -> 313673.09 | L81: =SUM(L79:L80) -> 442159.51 | M81: =SUM(M79:M80) -> 591033.59
A85: Supporting Schedules
A87: Working Capital Schedule
A88: Accounts Receivable | D88: - | E88: =E44 -> 44261 | F88: =F44 -> 48688 | G88: =G44 -> 56924 | H88: =H44 -> 69905 | I88: =((I26/365)*I15) -> 73950.288 | J88: =((J26/365)*J15) -> 83190.167 | K88: =((K26/365)*K15) -> 93584.542 | L88: =((L26/365)*L15) -> 105277.66 | M88: =((M26/365)*M15) -> 118431.81
A89: Inventory | D89: - | E89: =E45 -> 3742 | F89: =F45 -> 2500 | G89: =G45 -> 1246 | H89: =H45 -> 938 | I89: =((I27/365)*I16) -> 3076.8064 | J89: =((J27/365)*J16) -> 3461.2446 | K89: =((K27/365)*K16) -> 3893.7173 | L89: =((L27/365)*L16) -> 4380.2262 | M89: =((M27/365)*M16) -> 4927.523
A90: Accounts Payable | D90: - | E90: =E50 -> 19000 | F90: =F50 -> 18095 | G90: =G50 -> 21996 | H90: =H50 -> 27724 | I90: =((I27/365)*I17) -> 29260.581 | J90: =((J27/365)*J17) -> 32916.607 | K90: =((K27/365)*K17) -> 37029.444 | L90: =((L27/365)*L17) -> 41656.168 | M90: =((M27/365)*M17) -> 46860.988
A91: Net Working Capital (NWC) | D91: - | E91: =((E88+E89)-E90) -> 29003 | F91: =((F88+F89)-F90) -> 33093 | G91: =((G88+G89)-G90) -> 36174 | H91: =((H88+H89)-H90) -> 43119 | I91: =((I88+I89)-I90) -> 47766.514 | J91: =((J88+J89)-J90) -> 53734.804 | K91: =((K88+K89)-K90) -> 60448.815 | L91: =((L88+L89)-L90) -> 68001.723 | M91: =((M88+M89)-M90) -> 76498.345
A92: Change in NWC | D92: - | E92: 0 | F92: =(F91-E91) -> 4090 | G92: =(G91-F91) -> 3081 | H92: =(H91-G91) -> 6945 | I92: =(I91-H91) -> 4647.5138 | J92: =(J91-I91) -> 5968.2902 | K92: =(K91-J91) -> 6714.0111 | L92: =(L91-K91) -> 7552.9077 | M92: =(M91-L91) -> 8496.6221
A94: Depreciation Schedule
A95: PPE Opening | D95: - | E95: 70803 | F95: =E98 -> 87546 | G95: =F98 -> 109987 | H95: =G98 -> 154552 | I95: =H98 -> 229789 | J95: =I98 -> 236493.57 | K95: =J98 -> 242219.23 | L95: =K98 -> 247108.91 | M95: =L98 -> 251284.66
A96: Plus Capex | D96: - | E96: =E71*-1 -> 23886 | F96: =F71*-1 -> 28107 | G96: =G71*-1 -> 44477 | H96: =H71*-1 -> 64551 | I96: =I71*-1 -> 40255.25 | J96: =J71*-1 -> 40255.25 | K96: =K71*-1 -> 40255.25 | L96: =L71*-1 -> 40255.25 | M96: =M71*-1 -> 40255.25
A97: Less Depreciation | D97: - | E97: =E66 -> 14460 | F97: =F66 -> 13861 | G97: =G66 -> 22287 | H97: =H66 -> 34153 | I97: =I95*I12 -> 33550.679 | J97: =J95*J12 -> 34529.589 | K97: =K95*K12 -> 35365.573 | L97: =L95*L12 -> 36079.497 | M97: =M95*M12 -> 36689.184
A98: PPE Closing | D98: - | E98: =E46 -> 87546 | F98: =F46 -> 109987 | G98: =G46 -> 154552 | H98: =H46 -> 229789 | I98: =((I95+I96)-I97) -> 236493.57 | J98: =((J95+J96)-J97) -> 242219.23 | K98: =((K95+K96)-K97) -> 247108.91 | L98: =((L95+L96)-L97) -> 251284.66 | M98: =((M95+M96)-M97) -> 254850.73
A100: Debt & Interest Schedule | D100: -
A101: Debt Opening | D101: - | E101: 58146 | F101: =E103 -> 61270 | G101: =F103 -> 59965 | H101: =G103 -> 67127 | I101: =H103 -> 60588 | J101: =I103 -> 55672 | K101: =J103 -> 50756 | L101: =K103 -> 45840 | M101: =L103 -> 40924
A102: Issuance (repayment) | D102: - | E102: =E75 -> -9023 | F102: =F75 -> -2750 | G102: =G75 -> -4675 | H102: =H75 -> -3216 | I102: =I19 -> -4916 | J102: =J19 -> -4916 | K102: =K19 -> -4916 | L102: =L19 -> -4916 | M102: =M19 -> -4916
A103: Debt Closing | D103: - | E103: =E51 -> 61270 | F103: =F51 -> 59965 | G103: =G51 -> 67127 | H103: =H51 -> 60588 | I103: =SUM(I101:I102) -> 55672 | J103: =SUM(J101:J102) -> 50756 | K103: =SUM(K101:K102) -> 45840 | L103: =SUM(L101:L102) -> 40924 | M103: =SUM(M101:M102) -> 36008
A104: Interest Expense | D104: - | E104: - | F104: - | G104: - | H104: - | I104: - | J104: - | K104: - | L104: - | M104: -
A108: Charts and Graphs
A110: Revenue | D110: - | E110: =E26 -> 198270 | F110: =F26 -> 211915 | G110: =G26 -> 245122 | H110: =H26 -> 281724 | I110: =I26 -> 316924.61 | J110: =J26 -> 356523.44 | K110: =K26 -> 401070.04 | L110: =L26 -> 451182.6 | M110: =M26 -> 507556.58
A111: Gross Profit Margin (%) | D111: - | E111: =E28/E26 -> 0.68401674 | F111: =F28/F26 -> 0.68920086 | G111: =G28/G26 -> 0.69764444 | H111: =H28/H26 -> 0.68823742 | I111: =I28/I26 -> 0.68977487 | J111: =J28/J26 -> 0.68977487 | K111: =K28/K26 -> 0.68977487 | L111: =L28/L26 -> 0.68977487 | M111: =M28/M26 -> 0.68977487
A113: Operating Cash Flow | D113: - | E113: =E68 -> 86752 | F113: =F68 -> 88880 | G113: =G68 -> 108599 | H113: =H68 -> 141335 | I113: =I68 -> 145396.83 | J113: =J68 -> 159610.51 | K113: =K68 -> 176075 | L113: =L68 -> 194370.17 | M113: =M68 -> 214757.83
A114: Investing Cash Flow | D114: - | E114: =E72 -> -23886 | F114: =F72 -> -28107 | G114: =G72 -> -44477 | H114: =H72 -> -64551 | I114: =I72 -> -40255.25 | J114: =J72 -> -40255.25 | K114: =K72 -> -40255.25 | L114: =L72 -> -40255.25 | M114: =M72 -> -40255.25
A115: Financing Cash Flow | D115: - | E115: =E77 -> -39878 | F115: =F77 -> -23129 | G115: =G77 -> -19927 | H115: =H77 -> -19580 | I115: =I77 -> -25628.5 | J115: =J77 -> -25628.5 | K115: =K77 -> -25628.5 | L115: =L77 -> -25628.5 | M115: =M77 -> -25628.5
